{
  "filename": "CovFortress.are",
  "name": "Covenant Fortress",
  "listing": "{ ALL } Drinlinda Covenant Fortress",
  "range": "1500       1599",
  "rooms": {
    "1500": {
      "vnum": "1500",
      "title": "At the Fortress Barbican",
      "description": "The Covenant fortress' entrance is wedged between the mountain\nstone on the east and west sides with the only passable ways\nbeing north to the fortress ward or south to the Blight.  The\nentire fortress was constructed partially within the mountains\nfor greater defense, and a heavy spiked adamantite portcullis\nlooms overhead, ready to drop down as a second layer of defense\nbehind the massive adamantite studded ironwood doors.  A third layer\nof defense in the form of another set of studded ironwood doors behind\nthe portcullis.  In addition to these defenses, a wooden palisade stands\nat an angle facing outwards, ready to bring charges to a bloody halt.",
      "flags": [
        "ROOM_INDOORS",
        "ROOM_NO_SUMMON"
      ],
      "sector": "SECT_INSIDE",
      "exits": {
        "north": {
          "keywords": [],
          "state": [],
          "key": "0",
          "vnum": "1501"
        },
        "south": {
          "keywords": [],
          "state": [],
          "key": "0",
          "vnum": "17316"
        }
      },
      "extras": [],
      "hp_mod": 100,
      "mana_mod": 100
    },
    "1501": {
      "vnum": "1501",
      "title": "The Fortress Ward",
      "description": "The fortress ward is actually within the mountain itself, hollowed\nout by unknown means.  It is a massive chamber designed as a\nrally point for defending or in preparation for attacking.  To\nthe north is an entrance to go deeper into the mountain fortress.\nTo the east is the Covenant bestiary.",
      "flags": [
        "ROOM_INDOORS",
        "ROOM_NO_SUMMON"
      ],
      "sector": "SECT_INSIDE",
      "exits": {
        "north": {
          "keywords": [],
          "state": [],
          "key": "0",
          "vnum": "1502"
        },
        "east": {
          "keywords": [],
          "state": [
            "IS_DOOR"
          ],
          "key": "0",
          "vnum": "1536"
        },
        "south": {
          "keywords": [],
          "state": [],
          "key": "0",
          "vnum": "1500"
        }
      },
      "extras": [],
      "hp_mod": 100,
      "mana_mod": 100
    },
    "1502": {
      "vnum": "1502",
      "title": "A Dark Hallway",
      "description": "The hallway is fairly bland and the only things to see are the\neverburning torches lining the walls.  It is very quiet in here,\nthe only sounds that can be heard are the echoes from your own\nmovements.  A ladder made of what appears to be darkened mithril\nleads upwards and downwards.  Two doorways, one to the east and\none to the west lead off into other parts of the fortress.",
      "flags": [
        "ROOM_INDOORS",
        "ROOM_NO_SUMMON"
      ],
      "sector": "SECT_INSIDE",
      "exits": {
        "east": {
          "keywords": [],
          "state": [],
          "key": "0",
          "vnum": "1511"
        },
        "south": {
          "keywords": [],
          "state": [],
          "key": "0",
          "vnum": "1501"
        },
        "west": {
          "keywords": [],
          "state": [],
          "key": "0",
          "vnum": "1512"
        },
        "up": {
          "keywords": [],
          "state": [],
          "key": "0",
          "vnum": "1503"
        },
        "down": {
          "keywords": [],
          "state": [],
          "key": "0",
          "vnum": "1508"
        }
      },
      "extras": [],
      "hp_mod": 100,
      "mana_mod": 100
    },
    "1503": {
      "vnum": "1503",
      "title": "A Dark Hallway",
      "description": "The hallway is fairly bland and the only things to see are the\neverburning torches lining the walls.  It is very quiet in here,\nthe only sounds that can be heard are the echoes from your own\nmovements.  A doorway to the west leads to a room filled with\ncheap looking bunks while a doorway to the east leads to room\nfilled with more expensive looking bunks.",
      "flags": [
        "ROOM_INDOORS",
        "ROOM_NO_SUMMON"
      ],
      "sector": "SECT_INSIDE",
      "exits": {
        "north": {
          "keywords": [],
          "state": [],
          "key": "0",
          "vnum": "1504"
        },
        "east": {
          "keywords": [],
          "state": [],
          "key": "0",
          "vnum": "1516"
        },
        "west": {
          "keywords": [],
          "state": [],
          "key": "0",
          "vnum": "1515"
        },
        "down": {
          "keywords": [],
          "state": [],
          "key": "0",
          "vnum": "1502"
        }
      },
      "extras": [],
      "hp_mod": 100,
      "mana_mod": 100
    },
    "1504": {
      "vnum": "1504",
      "title": "A Dark Hallway",
      "description": "The hallway is fairly bland and the only things to see are the\neverburning torches lining the walls.  It is very quiet in here,\nthe only sounds that can be heard are the echoes from your own\nmovements.  To the west is a doorway leading to a room filled with\nbookshelves and to the east leads to a room with dozens of\nceremonial weapons and shields hanging on the walls.",
      "flags": [
        "ROOM_INDOORS",
        "ROOM_NO_SUMMON"
      ],
      "sector": "SECT_INSIDE",
      "exits": {
        "north": {
          "keywords": [],
          "state": [],
          "key": "0",
          "vnum": "1505"
        },
        "east": {
          "keywords": [],
          "state": [],
          "key": "0",
          "vnum": "1518"
        },
        "south": {
          "keywords": [],
          "state": [],
          "key": "0",
          "vnum": "1503"
        },
        "west": {
          "keywords": [],
          "state": [],
          "key": "0",
          "vnum": "1517"
        }
      },
      "extras": [],
      "hp_mod": 100,
      "mana_mod": 100
    },
    "1505": {
      "vnum": "1505",
      "title": "A Dark Hallway",
      "description": "The hallway is fairly bland and the only things to see are the\neverburning torches lining the walls.  It is very quiet in here,\nthe only sounds that can be heard are the echoes from your own\nmovements.",
      "flags": [
        "ROOM_INDOORS",
        "ROOM_NO_SUMMON"
      ],
      "sector": "SECT_INSIDE",
      "exits": {
        "north": {
          "keywords": [],
          "state": [],
          "key": "0",
          "vnum": "1506"
        },
        "south": {
          "keywords": [],
          "state": [],
          "key": "0",
          "vnum": "1504"
        }
      },
      "extras": [],
      "hp_mod": 100,
      "mana_mod": 100
    },
    "1506": {
      "vnum": "1506",
      "title": "A Dark Hallway",
      "description": "The hallway is fairly bland and the only things to see are the\neverburning torches lining the walls.  It is very quiet in here,\nthe only sounds that can be heard are the echoes from your own\nmovements.  To the west, a doorway leads to a room with an altar\nand a statue of a female knight and a sculpture of a beautiful\nwinged being.",
      "flags": [
        "ROOM_INDOORS",
        "ROOM_NO_SUMMON"
      ],
      "sector": "SECT_INSIDE",
      "exits": {
        "south": {
          "keywords": [],
          "state": [],
          "key": "0",
          "vnum": "1505"
        },
        "west": {
          "keywords": [],
          "state": [],
          "key": "0",
          "vnum": "1507"
        }
      },
      "extras": [],
      "hp_mod": 100,
      "mana_mod": 100
    },
    "1507": {
      "vnum": "1507",
      "title": "The Shrine of the Dark Covenant",
      "description": "The room is unlit with any major light source and is a little\ndark.  A half dozen candles scattered around the room provide\na little bit of light, and the statue of the Dark Maiden glows\nwith a soft white light as it seems to smile at you and watch\nyou.  The walls have been carved to depict every single soldier\nsworn to the Covenant, a new face appearing by itself whenever\nsomeone is promoted to the Knighthood.  The eyes of the carvings\nare made of what appears to be precious gems and they glow without\nany light source behind them.  Three cushioned kneeling benches\nare arranged before the altar of this holy ground.  A doorway\nleads south to a room filled with cots.",
      "flags": [
        "ROOM_INDOORS",
        "ROOM_NO_SUMMON"
      ],
      "sector": "SECT_INSIDE",
      "exits": {
        "north": {
          "keywords": [],
          "state": [],
          "key": "0",
          "vnum": "1519"
        },
        "east": {
          "keywords": [],
          "state": [],
          "key": "0",
          "vnum": "1506"
        },
        "south": {
          "keywords": [],
          "state": [],
          "key": "0",
          "vnum": "1534"
        }
      },
      "extras": [],
      "hp_mod": 100,
      "mana_mod": 100
    },
    "1508": {
      "vnum": "1508",
      "title": "A Dark Hallway",
      "description": "The hallway is fairly bland and the only things to see are the\neverburning torches lining the walls.  It is very quiet in here,\nthe only sounds that can be heard are the echoes from your own\nmovements.  A darkened mithril ladder leading upwards is here,\nallowing access to the upper floors.  A room that is nearly pitch\nblack lies to the east, and a room filled with an assortment of\ntools lies to the west.",
      "flags": [
        "ROOM_INDOORS",
        "ROOM_NO_SUMMON"
      ],
      "sector": "SECT_INSIDE",
      "exits": {
        "north": {
          "keywords": [],
          "state": [],
          "key": "0",
          "vnum": "1509"
        },
        "east": {
          "keywords": [],
          "state": [],
          "key": "0",
          "vnum": "1520"
        },
        "west": {
          "keywords": [],
          "state": [],
          "key": "0",
          "vnum": "1521"
        },
        "up": {
          "keywords": [],
          "state": [],
          "key": "0",
          "vnum": "1502"
        }
      },
      "extras": [],
      "hp_mod": 100,
      "mana_mod": 100
    },
    "1509": {
      "vnum": "1509",
      "title": "A Dark Hallway",
      "description": "The hallway is fairly bland and the only things to see are the\neverburning torches lining the walls.  It is very quiet in here,\nthe only sounds that can be heard are the echoes from your own\nmovements.  To the east lies a very strange room that appears\nto be a miniature forest while the west has a doorway leading\nto what appears to be a very large conference room.",
      "flags": [
        "ROOM_INDOORS",
        "ROOM_NO_SUMMON"
      ],
      "sector": "SECT_INSIDE",
      "exits": {
        "north": {
          "keywords": [],
          "state": [],
          "key": "0",
          "vnum": "1510"
        },
        "east": {
          "keywords": [],
          "state": [],
          "key": "0",
          "vnum": "1522"
        },
        "south": {
          "keywords": [],
          "state": [],
          "key": "0",
          "vnum": "1508"
        },
        "west": {
          "keywords": [],
          "state": [],
          "key": "0",
          "vnum": "1523"
        }
      },
      "extras": [],
      "hp_mod": 100,
      "mana_mod": 100
    },
    "1510": {
      "vnum": "1510",
      "title": "A Dark Hallway",
      "description": "The hallway is fairly bland and the only things to see are the\neverburning torches lining the walls.  It is very quiet in here,\nthe only sounds that can be heard are the echoes from your own\nmovements.  To the east, a doorway leads to a very large room\nwith a bed and a lot of other things.  To the west is a similar\nroom with a couple of large beds and other items within.",
      "flags": [
        "ROOM_INDOORS",
        "ROOM_NO_SUMMON"
      ],
      "sector": "SECT_INSIDE",
      "exits": {
        "north": {
          "keywords": [],
          "state": [],
          "key": "0",
          "vnum": "1526"
        },
        "east": {
          "keywords": [],
          "state": [],
          "key": "0",
          "vnum": "1524"
        },
        "south": {
          "keywords": [],
          "state": [],
          "key": "0",
          "vnum": "1509"
        },
        "west": {
          "keywords": [],
          "state": [],
          "key": "0",
          "vnum": "1525"
        }
      },
      "extras": [],
      "hp_mod": 100,
      "mana_mod": 100
    },
    "1511": {
      "vnum": "1511",
      "title": "A Dark Hallway",
      "description": "The hallway is fairly bland and the only things to see are the\neverburning torches lining the walls.  It is very quiet in here,\nthe only sounds that can be heard are the echoes from your own\nmovements.  To the south is what looks like a training room.",
      "flags": [
        "ROOM_INDOORS",
        "ROOM_NO_SUMMON"
      ],
      "sector": "SECT_INSIDE",
      "exits": {
        "south": {
          "keywords": [],
          "state": [],
          "key": "0",
          "vnum": "1513"
        },
        "west": {
          "keywords": [],
          "state": [],
          "key": "0",
          "vnum": "1502"
        }
      },
      "extras": [],
      "hp_mod": 100,
      "mana_mod": 100
    },
    "1512": {
      "vnum": "1512",
      "title": "A Dark Hallway",
      "description": "The hallway is fairly bland and the only things to see are the\neverburning torches lining the walls.  It is very quiet in here,\nthe only sounds that can be heard are the echoes from your own\nmovements.  To the south is what looks to be some sort of\nstockroom.  To the west is a bar.",
      "flags": [
        "ROOM_INDOORS",
        "ROOM_NO_SUMMON"
      ],
      "sector": "SECT_INSIDE",
      "exits": {
        "east": {
          "keywords": [],
          "state": [],
          "key": "0",
          "vnum": "1502"
        },
        "south": {
          "keywords": [],
          "state": [],
          "key": "0",
          "vnum": "1514"
        },
        "west": {
          "keywords": [],
          "state": [],
          "key": "0",
          "vnum": "1538"
        }
      },
      "extras": [],
      "hp_mod": 100,
      "mana_mod": 100
    },
    "1513": {
      "vnum": "1513",
      "title": "Training Room",
      "description": "This room is filled with a large number of training utilities.\nWooden dummies that spin and wobble, stationary wooden dummies,\nstraw dummies, bales of hay with targets attached to them, and\npendulum style archery targets adorn the walls and floor of the\nroom.  A strange divine aura nullifies all magic cast in here.",
      "flags": [
        "ROOM_INDOORS",
        "ROOM_NO_SUMMON"
      ],
      "sector": "SECT_INSIDE",
      "exits": {
        "north": {
          "keywords": [],
          "state": [],
          "key": "0",
          "vnum": "1511"
        },
        "up": {
          "keywords": [],
          "state": [],
          "key": "0",
          "vnum": "1533"
        }
      },
      "extras": [],
      "hp_mod": 100,
      "mana_mod": 100
    },
    "1514": {
      "vnum": "1514",
      "title": "General Stockroom",
      "description": "The stockroom is filled with dozens upon dozens of shelves, each\none filled with assorted things that are needed by an army.\nTents, canteens, dry rations and other things are available.\nThe quartermaster sits behind a counter in the middle of the\nroom and you notice a sign on the counter.  To the west is\na room filled with massive iron cabinets.",
      "flags": [
        "ROOM_INDOORS",
        "ROOM_NO_SUMMON"
      ],
      "sector": "SECT_INSIDE",
      "exits": {
        "north": {
          "keywords": [],
          "state": [],
          "key": "0",
          "vnum": "1512"
        },
        "west": {
          "keywords": [],
          "state": [],
          "key": "0",
          "vnum": "1537"
        },
        "up": {
          "keywords": [],
          "state": [],
          "key": "0",
          "vnum": "1532"
        }
      },
      "extras": [
        {
          "keywords": [
            "sign"
          ],
          "description": "It reads: I have tents, rations, canteens, sacks, and keys.  Just ask."
        }
      ],
      "hp_mod": 100,
      "mana_mod": 100
    },
    "1515": {
      "vnum": "1515",
      "title": "Squire Barracks",
      "description": "Covenant Squires, being the lowest on the ranking ladder, stay\nin this barracks when they're not training or being yelled at\nby superiors.  The barracks is conveniently located across the\nhall from the enlisted knights barracks so the more experienced\nknights can keep an eye on the ill trained squires.",
      "flags": [
        "ROOM_INDOORS",
        "ROOM_NO_SUMMON"
      ],
      "sector": "SECT_INSIDE",
      "exits": {
        "east": {
          "keywords": [],
          "state": [],
          "key": "0",
          "vnum": "1503"
        }
      },
      "extras": [],
      "hp_mod": 100,
      "mana_mod": 100
    },
    "1516": {
      "vnum": "1516",
      "title": "Knight Barracks",
      "description": "Covenant squires are an undisciplined lot, prone to arguing with\neach other or otherwise bothering each other if left alone too\nlong.  Their master knights always need to keep an eye on them,\nbut still give them a bit of privacy, so this barracks was built.\nLocated right across the hall from the Squire Barracks, the Knights\ncan rest here yet be close enough to storm the squire barracks\nand whap unruly squires if the need arises.  The bunks and furniture\nin here look to be more expensive than that of the Squire Barracks.\nA painting poster has been stuck to the wall.",
      "flags": [
        "ROOM_INDOORS",
        "ROOM_NO_SUMMON"
      ],
      "sector": "SECT_INSIDE",
      "exits": {
        "west": {
          "keywords": [],
          "state": [],
          "key": "0",
          "vnum": "1503"
        }
      },
      "extras": [
        {
          "keywords": [
            "poster"
          ],
          "description": "Ye gods.  Tis a poster of Supreme Commander Drinlinda that someone drew\nwith high quality paints.  It depicts Drinlinda in a slinky, low cut\nblack evening gown with thigh high slits cut up both sides of the dress.\nThe artist drew her facing at a slight angle to the left with her head\ntossed backwards, eyes closed, and both hands in her hair.  She seems\nto be wearing a pair of slippers with long heels.  The poster doesn't\nleave a lot to the imagination.  The poster seems a bit worn, as if\nit was hastily pulled down and hidden many times before inspection, and\nthen put up again later."
        }
      ],
      "hp_mod": 100,
      "mana_mod": 100
    },
    "1517": {
      "vnum": "1517",
      "title": "Covenant Library",
      "description": "The Covenant realizes that history at times does repeat itself\nand lessons of the past can be lessons for the future.  In light\nof this, the Covenant made a library to store a lot of old military\nhistory books in addition to their own books.  A very beautiful\nyoung human member of the Chaplain Corps serves as a librarian\nhere, swiftly finding requested books.  A sign is mounted on\nthe wall.",
      "flags": [
        "ROOM_INDOORS",
        "ROOM_NO_SUMMON"
      ],
      "sector": "SECT_INSIDE",
      "exits": {
        "east": {
          "keywords": [],
          "state": [],
          "key": "0",
          "vnum": "1504"
        }
      },
      "extras": [
        {
          "keywords": [
            "sign"
          ],
          "description": "Covenant Book -> Book of the Dark Covenant\nInfantry Manual -> Infantry Training Manual\nLeadership -> Book of Leadership\nArmy Book -> Book of the Army\nOfficer Manual -> Officer Training Manual\nGhost Manual -> Covert Operations Training Manual\nPathfinder Manual -> Pathfinder Training Manual\nChaplain Manual -> Chaplain Training Manual"
        }
      ],
      "hp_mod": 100,
      "mana_mod": 100
    },
    "1518": {
      "vnum": "1518",
      "title": "Infantry Recreation Room",
      "description": "Infantry are big, strong, and not always smart.  Their way of\nsolving any problem is to smash it.  As a result, members of\nthe other factions aren't exactly thrilled at having to share\nrecreation rooms with them, so this room was built.  Located\nacross from the library, the room has a mild sound dampener\nenchantment cast upon it so as to not disturb those in the\nlibrary.  The room is quite tidy, but scratches on the walls\nand small piles of smashed furniture betray the quite brutish\nnature of the infantry.",
      "flags": [
        "ROOM_INDOORS",
        "ROOM_NO_SUMMON"
      ],
      "sector": "SECT_INSIDE",
      "exits": {
        "west": {
          "keywords": [],
          "state": [],
          "key": "0",
          "vnum": "1504"
        }
      },
      "extras": [],
      "hp_mod": 100,
      "mana_mod": 100
    },
    "1519": {
      "vnum": "1519",
      "title": "Chaplain Corps Recreation Room",
      "description": "The Chaplain Corps, being the most reclusive Covenant branch\naside from the Covert Operations Ghosts, enjoys being close to\nthe heavens.  This recreation room was built next to the shrine\nso they could feel close to the heavens without hogging all the\nspace in the shrine.  Soft cushions, prayerbooks of several faiths,\nand manuscripts of healing and warfare lie in neat little piles\nin several locations around the room and the smell of burning\nincense gives the room a relaxing atmosphere.",
      "flags": [
        "ROOM_INDOORS",
        "ROOM_NO_SUMMON"
      ],
      "sector": "SECT_INSIDE",
      "exits": {
        "south": {
          "keywords": [],
          "state": [],
          "key": "0",
          "vnum": "1507"
        }
      },
      "extras": [],
      "hp_mod": 100,
      "mana_mod": 100
    },
    "1520": {
      "vnum": "1520",
      "title": "Covert Operations Recreation Room",
      "description": "The Covert Operations branch of the Covenant, commonly known\nas Ghosts, like training themselves constantly, practicing their\nskills of subterfuge and striking from the shadows.  The room\nis littered with a variety of locks of different makes, bells\nhung on ropes and other odd things that only Ghosts know about.",
      "flags": [
        "ROOM_INDOORS",
        "ROOM_NO_SUMMON"
      ],
      "sector": "SECT_INSIDE",
      "exits": {
        "east": {
          "keywords": [],
          "state": [],
          "key": "0",
          "vnum": "1539"
        },
        "west": {
          "keywords": [],
          "state": [],
          "key": "0",
          "vnum": "1508"
        }
      },
      "extras": [],
      "hp_mod": 100,
      "mana_mod": 100
    },
    "1521": {
      "vnum": "1521",
      "title": "Workshop",
      "description": "Covenant soldiers must know how to use and maintain weapons and\narmor as part of their training, but sometimes, weapons and armor\nsimply break from extended use.  Rather than completely depend\non an outside source completely for standard armaments, the\nCovenant has built this workshop to produce any type of armor or\nweaponry, provided the smiths have the materials they need.\nThis lets the Covenant soldiers not have to worry about running\ninto battle totally helpless due to a lack of equipment.",
      "flags": [
        "ROOM_INDOORS",
        "ROOM_NO_SUMMON"
      ],
      "sector": "SECT_INSIDE",
      "exits": {
        "east": {
          "keywords": [],
          "state": [],
          "key": "0",
          "vnum": "1508"
        }
      },
      "extras": [],
      "hp_mod": 100,
      "mana_mod": 100
    },
    "1522": {
      "vnum": "1522",
      "title": "Ranger Corps Recreation Room",
      "description": "Somehow, Lady Drinlinda managed to create a self contained forest\nin a room underneath a mountain.  This miniature forest has a\nsmall stream, medium sized trees, and even the very realistic\nillusion of a sky complete with sun and weather patterns that\nmimics the weather outside.  The Ranger Corps has made this its\nrecreation room, practicing their woodland skills and growing\nvarious herbs here for eating, healing, and selling to others.",
      "flags": [
        "ROOM_NO_SUMMON"
      ],
      "sector": "SECT_FOREST",
      "exits": {
        "east": {
          "keywords": [],
          "state": [],
          "key": "0",
          "vnum": "1535"
        },
        "west": {
          "keywords": [],
          "state": [],
          "key": "0",
          "vnum": "1509"
        }
      },
      "extras": [],
      "hp_mod": 100,
      "mana_mod": 100
    },
    "1523": {
      "vnum": "1523",
      "title": "Conference Room",
      "description": "Meeting delegates within cramped and sometimes smelly barracks\nisn't very polite, and having meetings crouched in the hallways\nor in the mess hall feels unprofessional, and so the Covenant\nbuilt this very lavish room with extremely soft, self cleaning\nand repairing carpets, a beautiful table, fancy well cushioned\nchairs, and a marvelous chandelier as well as a cart loaded with\nfood and drink.  The room is used often as a delegate meeting\nroom, or as a meeting room for Covenant officers.  A sign is\nmounted to a painted marble wall.",
      "flags": [
        "ROOM_INDOORS",
        "ROOM_NO_SUMMON"
      ],
      "sector": "SECT_FOREST",
      "exits": {
        "east": {
          "keywords": [],
          "state": [],
          "key": "0",
          "vnum": "1509"
        }
      },
      "extras": [
        {
          "keywords": [
            "sign"
          ],
          "description": "Do not fight, sleep in, or otherwise mess up this room with litter.  It\nis for meetings only, whether it be an officer meeting, delegate meeting,\nor any general army meeting."
        }
      ],
      "hp_mod": 100,
      "mana_mod": 100
    },
    "1524": {
      "vnum": "1524",
      "title": "General's Quarters",
      "description": "The General, being the highest ranked mortal of the Covenant,\nhas this very large private room all to themselves.  A large,\nwell stuffed bed made of cherrywood, a closet for holding uniforms,\na weapons and armor rack, and a personal latrine fill the room.\nThe room is well lit with a glowcrystal lamp hanging from the\nceiling.",
      "flags": [
        "ROOM_INDOORS",
        "ROOM_NO_SUMMON"
      ],
      "sector": "SECT_FOREST",
      "exits": {
        "west": {
          "keywords": [],
          "state": [],
          "key": "0",
          "vnum": "1510"
        }
      },
      "extras": [],
      "hp_mod": 100,
      "mana_mod": 100
    },
    "1525": {
      "vnum": "1525",
      "title": "Officers' Quarters",
      "description": "The highest ranking Covenant officers gain the use of this room,\nwhich is second only to the General's quarters in terms of comfort\nand lavishness.  Several soft bunks, unlike the hard as rock\nbunks in the Knight Barracks, line the walls along with personal\nfootlockers.  A glowcrystal lamp hangs from the ceiling and a\ndouble latrine is embedded into the wall beside the closets and\nweapons and armor racks.  There appears to be a painting on the\nwall.",
      "flags": [
        "ROOM_INDOORS",
        "ROOM_NO_SUMMON"
      ],
      "sector": "SECT_FOREST",
      "exits": {
        "east": {
          "keywords": [],
          "state": [],
          "key": "0",
          "vnum": "1510"
        }
      },
      "extras": [
        {
          "keywords": [
            "painting"
          ],
          "description": "Some officer obviously liked this painting of General Taraxipus.  The artist\npainted the General wearing nothing but a thin sash over her well endowed\nchest and the General's arms are crossed beneath.  The General's head is\ntilted down slightly towards the viewer and her eyes look up from beneath\nher bangs.  Mysterious and lovely."
        }
      ],
      "hp_mod": 100,
      "mana_mod": 100
    },
    "1526": {
      "vnum": "1526",
      "title": "A Dark Hallway",
      "description": "The hallway is fairly bland and the only things to see are the\neverburning torches lining the walls.  It is very quiet in here,\nthe only sounds that can be heard are the echoes from your own\nmovements.  To the east is a doorway leading to what appears to\nbe a dungeon, and to the west is a room that is filled with\ninterrogation instruments.",
      "flags": [
        "ROOM_INDOORS",
        "ROOM_NO_SUMMON"
      ],
      "sector": "SECT_FOREST",
      "exits": {
        "north": {
          "keywords": [],
          "state": [],
          "key": "0",
          "vnum": "1531"
        },
        "east": {
          "keywords": [],
          "state": [
            "IS_DOOR",
            "NOPASS"
          ],
          "key": "1544",
          "vnum": "1527"
        },
        "south": {
          "keywords": [],
          "state": [],
          "key": "0",
          "vnum": "1510"
        },
        "west": {
          "keywords": [],
          "state": [],
          "key": "0",
          "vnum": "1528"
        }
      },
      "extras": [],
      "hp_mod": 100,
      "mana_mod": 100
    },
    "1527": {
      "vnum": "1527",
      "title": "Dungeon",
      "description": "Like most dungeons, this dungeon is not well lit, has bars and\nlocks, and smells a bit funny.  Unlike most dungeons though,\nthis dungeon actually tries to let the prisoners feel comfortable,\nthough not too comfortable.  A long, lightly padded bench mounted\nto the wall and hanging from chains and a couple of immobile,\nenchanted buckets for latrines adorn the cell.",
      "flags": [
        "ROOM_INDOORS",
        "ROOM_NO_SUMMON"
      ],
      "sector": "SECT_FOREST",
      "exits": {
        "west": {
          "keywords": [],
          "state": [
            "IS_DOOR",
            "NOPASS"
          ],
          "key": "1544",
          "vnum": "1526"
        }
      },
      "extras": [],
      "hp_mod": 100,
      "mana_mod": 100
    },
    "1528": {
      "vnum": "1528",
      "title": "Interrogation Room",
      "description": "Occasionally, prisoners have information that the Covenant may\nwant, but the prisoners refuse to give.  To solve this problem,\nthis interrogation room was built.  The long tables have a variety\nof non lethal interrogation implements usable only by Covenant\nsoldiers.  Finger clamps, hot irons, a rod of shocking, and other\nitems are scattered on the tables along with some potions of\nhealing and regeneration and bottles of medicinal herbs.  A stretching\nrack and a chair with clamps sit near the back of the room, both\npolished and wiped clean of sweat and other bodily fluids that prisoners\nsometimes deposit on them.",
      "flags": [
        "ROOM_INDOORS",
        "ROOM_NO_SUMMON"
      ],
      "sector": "SECT_FOREST",
      "exits": {
        "east": {
          "keywords": [],
          "state": [],
          "key": "0",
          "vnum": "1526"
        }
      },
      "extras": [],
      "hp_mod": 100,
      "mana_mod": 100
    },
    "1529": {
      "vnum": "1529",
      "title": "Portal Room",
      "description": "This room is used mainly by the Covert Operations as a way of\ninserting soldiers into strategic places throughout Thera.  The\nentire room is marked with holy symbols and runes, each glowing\nwith power.  The way north leads to the hallway and an inscription\nis carved on the floor around a portal.",
      "flags": [
        "ROOM_INDOORS",
        "ROOM_NO_SUMMON"
      ],
      "sector": "SECT_FOREST",
      "exits": {
        "north": {
          "keywords": [],
          "state": [],
          "key": "0",
          "vnum": "1508"
        },
        "east": {
          "keywords": [],
          "state": [
            "IS_DOOR"
          ],
          "key": "0",
          "vnum": "10601"
        },
        "south": {
          "keywords": [],
          "state": [
            "IS_DOOR"
          ],
          "key": "0",
          "vnum": "8824"
        },
        "west": {
          "keywords": [],
          "state": [
            "IS_DOOR"
          ],
          "key": "0",
          "vnum": "3014"
        },
        "up": {
          "keywords": [],
          "state": [
            "IS_DOOR"
          ],
          "key": "0",
          "vnum": "711"
        },
        "down": {
          "keywords": [],
          "state": [
            "IS_DOOR"
          ],
          "key": "0",
          "vnum": "27815"
        }
      },
      "extras": [],
      "hp_mod": 100,
      "mana_mod": 100
    },
    "1530": {
      "vnum": "1530",
      "title": "Execution Chamber",
      "description": "This room is not mentioned much by the Covenant soldiers.  It's\na room of final judgement, where Covenant soldiers who absolutely\nhave failed their duties face a firing squad of elite female\ndrow soldiers armed with crossbows with negative material tipped\nbolts.  For the Covenant soldier that has repeatedly failed their\nduty, this is the last place they see before going to the great\nbeyond.  A number of caskets are stacked in a corner and one\nwall has chains attached to it, with a blindfold lying on the\nfloor.",
      "flags": [
        "ROOM_INDOORS",
        "ROOM_NO_SUMMON"
      ],
      "sector": "SECT_FOREST",
      "exits": {
        "west": {
          "keywords": [],
          "state": [
            "IS_DOOR"
          ],
          "key": "0",
          "vnum": "1511"
        }
      },
      "extras": [],
      "hp_mod": 100,
      "mana_mod": 100
    },
    "1531": {
      "vnum": "1531",
      "title": "Chamber of Judgement",
      "description": "Occsionally, issues arise that require a Covenant tribunal to\ndetermine the punishment of a soldier.  The highest three mortal\nmembers of the Covenant come here to pass judgement upon soldiers\nthat have gotten themselves in trouble.",
      "flags": [
        "ROOM_INDOORS",
        "ROOM_NO_SUMMON"
      ],
      "sector": "SECT_FOREST",
      "exits": {
        "south": {
          "keywords": [],
          "state": [],
          "key": "0",
          "vnum": "1526"
        }
      },
      "extras": [],
      "hp_mod": 100,
      "mana_mod": 100
    },
    "1532": {
      "vnum": "1532",
      "title": "Western Siege Weapon Tower",
      "description": "Nestled above the stockroom inside the mountain, this \"tower\"\nisn't a tower at all since the entire fortress is built into\nthe mountain.  A series of powerful ballistae mounted on rotating\nplatforms are arranged on sliding rails, each one ready to fire\nat foes outside.  The side of the mountain they are pointing\nat has been completely carved out, making this room a bit drafty\nbut allowing for the ballistae and also archers to fire outside.\nLarge canvas bags filled with sand and small rocks lie in orderly\npiles beside racks of bows and crossbows, barrels of filled quivers\nand bolt boxes, ballista bolts, and ballista accessories.",
      "flags": [
        "ROOM_INDOORS",
        "ROOM_NO_SUMMON"
      ],
      "sector": "SECT_INSIDE",
      "exits": {
        "down": {
          "keywords": [],
          "state": [],
          "key": "0",
          "vnum": "1514"
        }
      },
      "extras": [],
      "hp_mod": 100,
      "mana_mod": 100
    },
    "1533": {
      "vnum": "1533",
      "title": "Eastern Siege Weapon Tower",
      "description": "Nestled above the training room inside the mountain, this \"tower\"\nisn't a tower at all since the entire fortress is built into\nthe mountain.  A series of powerful ballistae mounted on rotating\nplatforms are arranged on sliding rails, each one ready to fire\nat foes outside.  The side of the mountain they are pointing\nat has been completely carved out, making this room a bit drafty\nbut allowing for the ballistae and also archers to fire outside.\nLarge canvas bags filled with sand and small rocks lie in orderly\npiles beside racks of bows and crossbows, barrels of filled quivers\nand bolt boxes, ballista bolts, and ballista accessories.",
      "flags": [
        "ROOM_INDOORS",
        "ROOM_NO_SUMMON"
      ],
      "sector": "SECT_INSIDE",
      "exits": {
        "down": {
          "keywords": [],
          "state": [],
          "key": "0",
          "vnum": "1513"
        }
      },
      "extras": [],
      "hp_mod": 100,
      "mana_mod": 100
    },
    "1534": {
      "vnum": "1534",
      "title": "Infirmary",
      "description": "Located just south of the shrine and the Chaplain Corps' recreation\nroom, the infirmary is where the injured are taken.  Sometimes,\nif a foe has proved themselves honorable, they are taken here\nto be healed also.",
      "flags": [
        "ROOM_INDOORS",
        "ROOM_NO_SUMMON"
      ],
      "sector": "SECT_INSIDE",
      "exits": {
        "north": {
          "keywords": [],
          "state": [],
          "key": "0",
          "vnum": "1507"
        }
      },
      "extras": [],
      "hp_mod": 100,
      "mana_mod": 100
    },
    "1535": {
      "vnum": "1535",
      "title": "Underground Farm",
      "description": "This underground farm supplements the Covenant food supply.\nThe illusion of a sky and the real weather that affects the Ranger\nCorps' recreation room also affects this small farm where rangers\ngrow crops and tend to poultry coops and a small herd of cows\nand sheep and a sty of pigs.  A small sheepdog can be seen running\naround herding the sheep and cows away from the Ranger Corps'\nrecreation room.",
      "flags": [
        "ROOM_NO_SUMMON"
      ],
      "sector": "SECT_FIELD",
      "exits": {
        "west": {
          "keywords": [],
          "state": [],
          "key": "0",
          "vnum": "1522"
        }
      },
      "extras": [],
      "hp_mod": 100,
      "mana_mod": 100
    },
    "1536": {
      "vnum": "1536",
      "title": "Covenant Bestiary",
      "description": "The battledragons and nightmares of the Covenant army dwell here,\nliving without cages or stables of any sort.  Piles of food\nfor either type of creature are piled in the corners and a large\nspring welling up from underground into a water trough provides\nthem with water.  The creatures themselves do whatever they want\nto do, and when nature calls, they have a large trough filled with\ndirt which channels downwards to the underground farm to use the\nwaste as fertilizer.",
      "flags": [
        "ROOM_INDOORS",
        "ROOM_NO_SUMMON"
      ],
      "sector": "SECT_INSIDE",
      "exits": {
        "west": {
          "keywords": [],
          "state": [
            "IS_DOOR"
          ],
          "key": "0",
          "vnum": "1501"
        }
      },
      "extras": [],
      "hp_mod": 100,
      "mana_mod": 100
    },
    "1537": {
      "vnum": "1537",
      "title": "Armory",
      "description": "A majority of the heavy weaponry and armor of the Covenant is kept\nhere in locked weapons lockers.  The entire room is well lit and\neach locker is polished to a gleaming shine.  The armor and weapons\nnot located in the lockers are arranged neatly on weapon and armor\nstands.",
      "flags": [
        "ROOM_INDOORS",
        "ROOM_NO_SUMMON"
      ],
      "sector": "SECT_INSIDE",
      "exits": {
        "east": {
          "keywords": [],
          "state": [],
          "key": "0",
          "vnum": "1514"
        }
      },
      "extras": [],
      "hp_mod": 100,
      "mana_mod": 100
    },
    "1538": {
      "vnum": "1538",
      "title": "The Thirsty Soldier Bar",
      "description": "Serving light brews brewed by the rangers in the underground farm, the\nCovenant bar provides refreshments for thirsty soldiers who have been\nrelieved of duty.  The bar is well decorated with various paintings of\nthe lovely lasses of the Covenant in full battle dress and paintings of\nfamous battles won by the Covenant.  A sign is mounted on the wall.",
      "flags": [
        "ROOM_INDOORS",
        "ROOM_NO_SUMMON"
      ],
      "sector": "SECT_INSIDE",
      "exits": {
        "east": {
          "keywords": [],
          "state": [],
          "key": "0",
          "vnum": "1512"
        }
      },
      "extras": [
        {
          "keywords": [
            "sign"
          ],
          "description": "Just say \"Beer please\" and I'll give you a beer.  It's all paid for."
        }
      ],
      "hp_mod": 100,
      "mana_mod": 100
    },
    "1539": {
      "vnum": "1539",
      "title": "Intelligence Office",
      "description": "Maps, hastily scribbled notes, diagrams, and sketches of various people\nand monsters are scattered all over the walls and even the ceiling of this\nroom.  Covert Operatives run around comparing notes and sending runners to\nthe officers, making this place quite noisy.  The room is lit with a couple\nof glowcrystal lamps, making it fairly well lit.",
      "flags": [
        "ROOM_INDOORS",
        "ROOM_NO_SUMMON"
      ],
      "sector": "SECT_INSIDE",
      "exits": {
        "west": {
          "keywords": [],
          "state": [],
          "key": "0",
          "vnum": "1520"
        }
      },
      "extras": [],
      "hp_mod": 100,
      "mana_mod": 100
    }
  }
}